[{"name":"Abdelwa3a","race":"Persan","age":43}][{"name":"Brad Pitt","filmsPlayed":["Once upon a time in Hollywood","Fight Club"]}][{"name":"Abdelwa3a","race":"Persan","age":43},{"firstName":"Ayoub <3","lastName":"Fakir","salary":150000,"numberOfChildren":23}][{"name":"Abdelwa3a","race":"Persan","age":43},{"firstName":"Ayoub <3","lastName":"Fakir","salary":150000,"numberOfChildren":23},{"brand":"Tesla","countryOfBirth":"USA","maxSpeed":250,"speeds":43}][{"name":"Abdelwa3a","race":"Persan","age":43},{"firstName":"Ayoub <3","lastName":"Fakir","salary":150000,"numberOfChildren":23},{"brand":"Tesla","countryOfBirth":"USA","maxSpeed":250,"speeds":43},{"mainActors":["Brad Pitt","Leonardo DiCaprio","Ayoub Fakir"],"dateOfRelease":"2019-07-25T22:00:00Z"}]